messente_api/__init__.py
messente_api/api_client.py
messente_api/api_response.py
messente_api/configuration.py
messente_api/exceptions.py
messente_api/py.typed
messente_api/rest.py
messente_api/api/__init__.py
messente_api/api/account_balance_api.py
messente_api/api/blacklist_api.py
messente_api/api/bulk_messaging_api.py
messente_api/api/contacts_api.py
messente_api/api/delivery_report_api.py
messente_api/api/groups_api.py
messente_api/api/number_lookup_api.py
messente_api/api/number_verification_api.py
messente_api/api/omnimessage_api.py
messente_api/api/pricing_api.py
messente_api/api/statistics_api.py
messente_api/api/whats_app_templates_api.py
messente_api/models/__init__.py
messente_api/models/bulk_omni_message_create_success_response.py
messente_api/models/bulk_omni_message_create_success_response_messages_inner.py
messente_api/models/bulk_omnimessage.py
messente_api/models/channel.py
messente_api/models/contact_envelope.py
messente_api/models/contact_fields.py
messente_api/models/contact_list_envelope.py
messente_api/models/contact_response_fields.py
messente_api/models/contact_update_fields.py
messente_api/models/delivery_report_response.py
messente_api/models/delivery_result.py
messente_api/models/error_code_omnichannel.py
messente_api/models/error_code_omnichannel_machine.py
messente_api/models/error_code_phonebook.py
messente_api/models/error_code_statistics.py
messente_api/models/error_item_number_lookup.py
messente_api/models/error_item_number_lookup_error.py
messente_api/models/error_item_omnichannel.py
messente_api/models/error_item_phonebook.py
messente_api/models/error_item_statistics.py
messente_api/models/error_number_lookup.py
messente_api/models/error_omnichannel.py
messente_api/models/error_phonebook.py
messente_api/models/error_statistics.py
messente_api/models/error_title_omnichannel.py
messente_api/models/error_title_phonebook.py
messente_api/models/fetch_blacklist_success.py
messente_api/models/group_envelope.py
messente_api-2.5.2.dist-info/METADATA
messente_api-2.5.2.dist-info/WHEEL
messente_api-2.5.2.dist-info/top_level.txt
messente_api-2.5.2.dist-info/RECORD
