Metadata-Version: 2.4
Name: messente-api
Version: 2.5.2
Summary: Messente API
Home-page: https://github.com/messente/messente-api-python
Author: Messente
Author-email: messente@messente.com
License: Apache-2.0
Keywords: viber,sms,whatsapp,phonebook
Requires-Dist: urllib3<3.0.0,>=1.25.3
Requires-Dist: python-dateutil>=2.8.2
Requires-Dist: pydantic>=2
Requires-Dist: typing-extensions>=4.7.1
Dynamic: author
Dynamic: author-email
Dynamic: description
Dynamic: description-content-type
Dynamic: home-page
Dynamic: keywords
Dynamic: license
Dynamic: requires-dist
Dynamic: summary
